{
    "dependencies": [
        {
            "name": "kube-prometheus",
            "source": {
                "git": {
                    "remote": "https://github.com/coreos/kube-prometheus",
                    "subdir": "jsonnet/kube-prometheus"
                }
            },
            "version": "a249b1c43424410daaf5b4e8c8a3c3e85a018e12"
        },
        {
            "name": "ksonnet",
            "source": {
                "git": {
                    "remote": "https://github.com/ksonnet/ksonnet-lib",
                    "subdir": ""
                }
            },
            "version": "d03da231d6c8bd74437b74a1e9e8b966f13dffa2"
        },
        {
            "name": "kubernetes-mixin",
            "source": {
                "git": {
                    "remote": "https://github.com/kubernetes-monitoring/kubernetes-mixin",
                    "subdir": ""
                }
            },
            "version": "e773265e7ca17a9a5a13e4e8d5ac911470b46560"
        },
        {
            "name": "grafonnet",
            "source": {
                "git": {
                    "remote": "https://github.com/grafana/grafonnet-lib",
                    "subdir": "grafonnet"
                }
            },
            "version": "a6896d19aedc46ecf80dd64967191b9fd6f75f45"
        },
        {
            "name": "grafana-builder",
            "source": {
                "git": {
                    "remote": "https://github.com/kausalco/public",
                    "subdir": "grafana-builder"
                }
            },
            "version": "a73d6c3e7f5804fc7a16f592b42a62384605046c"
        },
        {
            "name": "grafana",
            "source": {
                "git": {
                    "remote": "https://github.com/brancz/kubernetes-grafana",
                    "subdir": "grafana"
                }
            },
            "version": "b6db6bdbdc8d7f2f8834a8044897ea6322a0f6ad"
        },
        {
            "name": "prometheus-operator",
            "source": {
                "git": {
                    "remote": "https://github.com/coreos/prometheus-operator",
                    "subdir": "jsonnet/prometheus-operator"
                }
            },
            "version": "1b202471cb9847282198ec008b58bd7c34d9d2ff"
        },
        {
            "name": "etcd-mixin",
            "source": {
                "git": {
                    "remote": "https://github.com/coreos/etcd",
                    "subdir": "Documentation/etcd-mixin"
                }
            },
            "version": "71881a423fa58b8a37536e47ce82c8e3da61e9a0"
        }
    ]
}
